writefile_run/__init__.py
writefile_run-0.3.dist-info/DESCRIPTION.rst
writefile_run-0.3.dist-info/METADATA
writefile_run-0.3.dist-info/RECORD
writefile_run-0.3.dist-info/WHEEL
writefile_run-0.3.dist-info/metadata.json
writefile_run-0.3.dist-info/top_level.txt
